adafruit_wiz.py
adafruit_circuitpython_wiz-1.1.2.dist-info/licenses/LICENSE
adafruit_circuitpython_wiz-1.1.2.dist-info/METADATA
adafruit_circuitpython_wiz-1.1.2.dist-info/WHEEL
adafruit_circuitpython_wiz-1.1.2.dist-info/top_level.txt
adafruit_circuitpython_wiz-1.1.2.dist-info/RECORD
