Metadata-Version: 2.4
Name: adafruit-circuitpython-wiz
Version: 1.1.2
Summary: CircuitPython helper library for Wiz connected lights
Author-email: Adafruit Industries <circuitpython@adafruit.com>
License: MIT
Project-URL: Homepage, https://github.com/adafruit/Adafruit_CircuitPython_Wiz
Keywords: adafruit,blinka,circuitpython,micropython,wiz,light,lights,led,rgb,smartlight,iot,connected,wizconnected,easyconnect
Classifier: Intended Audience :: Developers
Classifier: Topic :: Software Development :: Libraries
Classifier: Topic :: Software Development :: Embedded Systems
Classifier: Topic :: System :: Hardware
Classifier: License :: OSI Approved :: MIT License
Classifier: Programming Language :: Python :: 3
License-File: LICENSE
Requires-Dist: Adafruit-Blinka
Requires-Dist: adafruit-circuitpython-connectionmanager
Provides-Extra: optional
Dynamic: license-file
